MANIFEST.in
README.md
setup.py
pyTsetlinMachine/ConvolutionalTsetlinMachine.c
pyTsetlinMachine/ConvolutionalTsetlinMachine.h
pyTsetlinMachine/IndexedTsetlinMachine.c
pyTsetlinMachine/IndexedTsetlinMachine.h
pyTsetlinMachine/MultiClassConvolutionalTsetlinMachine.c
pyTsetlinMachine/MultiClassConvolutionalTsetlinMachine.h
pyTsetlinMachine/Tools.c
pyTsetlinMachine/Tools.h
pyTsetlinMachine/__init__.py
pyTsetlinMachine/fast_rand.h
pyTsetlinMachine/tm.py
pyTsetlinMachine/tools.py
pyTsetlinMachine.egg-info/PKG-INFO
pyTsetlinMachine.egg-info/SOURCES.txt
pyTsetlinMachine.egg-info/dependency_links.txt
pyTsetlinMachine.egg-info/top_level.txt