Metadata-Version: 1.0
Name: pyTsetlinMachine
Version: 0.4.0
Summary: Implements the Tsetlin Machine, Convolutional Tsetlin Machine and Regression Tsetlin Machine, with support for continuous features.
Home-page: https://github.com/cair/pyTsetlinMachine/
Author: Ole-Christoffer Granmo
Author-email: ole.granmo@uia.no
License: MIT
Keywords: pattern-recognition machine-learning interpretable-machine-learning rule-based-machine-learning propositional-logic tsetlin-machine regression convolution
Platform: UNKNOWN
